{
    "asset": {
        "format": "jpg",
        "id": "9187b6ed6f23e5b165a131b6df75ce07",
        "name": "7fe5a62bdfd046be9662d1f68c194869.jpg",
        "path": "file:C:/Repositories/BS.ReceiptAnalyzer/machine-learning-data/receipt-recognize/images/7fe5a62bdfd046be9662d1f68c194869.jpg",
        "size": {
            "width": 750,
            "height": 1000
        },
        "state": 2,
        "type": 1
    },
    "regions": [
        {
            "id": "XYp52JfRi",
            "type": "POLYGON",
            "tags": [
                "receipt"
            ],
            "boundingBox": {
                "height": 995.6709956709957,
                "width": 727.2727272727273,
                "left": 1.0822510822510822,
                "top": 1.0822510822510822
            },
            "points": [
                {
                    "x": 208.87445887445887,
                    "y": 27.056277056277057
                },
                {
                    "x": 27.056277056277057,
                    "y": 282.46753246753246
                },
                {
                    "x": 1.0822510822510822,
                    "y": 550.8658008658009
                },
                {
                    "x": 1.0822510822510822,
                    "y": 966.4502164502164
                },
                {
                    "x": 358.2251082251082,
                    "y": 990.2597402597403
                },
                {
                    "x": 542.2077922077922,
                    "y": 996.7532467532468
                },
                {
                    "x": 721.8614718614718,
                    "y": 994.5887445887446
                },
                {
                    "x": 728.3549783549784,
                    "y": 737.012987012987
                },
                {
                    "x": 728.3549783549784,
                    "y": 524.8917748917748
                },
                {
                    "x": 724.025974025974,
                    "y": 182.9004329004329
                },
                {
                    "x": 724.025974025974,
                    "y": 1.0822510822510822
                },
                {
                    "x": 546.5367965367965,
                    "y": 1.0822510822510822
                },
                {
                    "x": 373.3766233766234,
                    "y": 18.3982683982684
                },
                {
                    "x": 312.7705627705628,
                    "y": 9.74025974025974
                }
            ]
        }
    ],
    "version": "2.2.0"
}