{
    "asset": {
        "format": "jpg",
        "id": "ba4b5e79071b21b71fa97f5d5367a626",
        "name": "697f8712b6ac49daaf41375a11ed0922.jpg",
        "path": "file:C:/Repositories/BS.ReceiptAnalyzer/machine-learning-data/receipt-recognize/images/697f8712b6ac49daaf41375a11ed0922.jpg",
        "size": {
            "width": 750,
            "height": 1000
        },
        "state": 2,
        "type": 1
    },
    "regions": [
        {
            "id": "lSx5tm58x",
            "type": "POLYGON",
            "tags": [
                "receipt"
            ],
            "boundingBox": {
                "height": 1000,
                "width": 506.4935064935065,
                "left": 117.96536796536796,
                "top": 0
            },
            "points": [
                {
                    "x": 122.2943722943723,
                    "y": 0
                },
                {
                    "x": 117.96536796536796,
                    "y": 208.87445887445887
                },
                {
                    "x": 126.62337662337669,
                    "y": 953.4632034632034
                },
                {
                    "x": 161.25541125541125,
                    "y": 1000
                },
                {
                    "x": 622.2943722943722,
                    "y": 1000
                },
                {
                    "x": 624.4588744588744,
                    "y": 602.8138528138528
                },
                {
                    "x": 624.4588744588744,
                    "y": 390.6926406926407
                },
                {
                    "x": 617.9653679653679,
                    "y": 0
                }
            ]
        }
    ],
    "version": "2.2.0"
}