{
    "asset": {
        "format": "png",
        "id": "53e5f6cd13ce205431aec9b96179070f",
        "name": "C_e69b98b0e748f18a69fc76fd611f7a.png",
        "path": "file:C:/Repositories/BS.ReceiptAnalyzer/machine-learning-data/receipt-partitioning/images/C_e69b98b0e748f18a69fc76fd611f7a.png",
        "size": {
            "width": 787,
            "height": 827
        },
        "state": 2,
        "type": 1
    },
    "regions": [
        {
            "id": "FZttQVa3Q",
            "type": "RECTANGLE",
            "tags": [
                "header"
            ],
            "boundingBox": {
                "height": 134.24248496993988,
                "width": 671.021052631579,
                "left": 76.9396052631579,
                "top": 628.1222444889779
            },
            "points": [
                {
                    "x": 76.9396052631579,
                    "y": 628.1222444889779
                },
                {
                    "x": 747.9606578947369,
                    "y": 628.1222444889779
                },
                {
                    "x": 747.9606578947369,
                    "y": 762.3647294589179
                },
                {
                    "x": 76.9396052631579,
                    "y": 762.3647294589179
                }
            ]
        },
        {
            "id": "yPgfXnkGn",
            "type": "RECTANGLE",
            "tags": [
                "product"
            ],
            "boundingBox": {
                "height": 67.9498997995992,
                "width": 674.3347368421053,
                "left": 75.28276315789473,
                "top": 540.2845691382765
            },
            "points": [
                {
                    "x": 75.28276315789473,
                    "y": 540.2845691382765
                },
                {
                    "x": 749.6175,
                    "y": 540.2845691382765
                },
                {
                    "x": 749.6175,
                    "y": 608.2344689378757
                },
                {
                    "x": 75.28276315789473,
                    "y": 608.2344689378757
                }
            ]
        },
        {
            "id": "FHOekEJA2",
            "type": "RECTANGLE",
            "tags": [
                "product"
            ],
            "boundingBox": {
                "height": 43.09018036072144,
                "width": 675.9915789473685,
                "left": 75.28276315789473,
                "top": 510.4529058116232
            },
            "points": [
                {
                    "x": 75.28276315789473,
                    "y": 510.4529058116232
                },
                {
                    "x": 751.2743421052631,
                    "y": 510.4529058116232
                },
                {
                    "x": 751.2743421052631,
                    "y": 553.5430861723447
                },
                {
                    "x": 75.28276315789473,
                    "y": 553.5430861723447
                }
            ]
        },
        {
            "id": "IMnGHfnhF",
            "type": "RECTANGLE",
            "tags": [
                "product"
            ],
            "boundingBox": {
                "height": 48.06212424849699,
                "width": 675.9915789473686,
                "left": 75.28276315789473,
                "top": 473.9919839679359
            },
            "points": [
                {
                    "x": 75.28276315789473,
                    "y": 473.9919839679359
                },
                {
                    "x": 751.2743421052633,
                    "y": 473.9919839679359
                },
                {
                    "x": 751.2743421052633,
                    "y": 522.0541082164328
                },
                {
                    "x": 75.28276315789473,
                    "y": 522.0541082164328
                }
            ]
        },
        {
            "id": "WgnFB0fD_",
            "type": "RECTANGLE",
            "tags": [
                "vat-summary"
            ],
            "boundingBox": {
                "height": 172.36072144288576,
                "width": 679.3052631578947,
                "left": 76.9396052631579,
                "top": 306.60320641282567
            },
            "points": [
                {
                    "x": 76.9396052631579,
                    "y": 306.60320641282567
                },
                {
                    "x": 756.2448684210526,
                    "y": 306.60320641282567
                },
                {
                    "x": 756.2448684210526,
                    "y": 478.9639278557114
                },
                {
                    "x": 76.9396052631579,
                    "y": 478.9639278557114
                }
            ]
        },
        {
            "id": "Qmvd6KJp9",
            "type": "RECTANGLE",
            "tags": [
                "price-summary"
            ],
            "boundingBox": {
                "height": 84.52304609218437,
                "width": 684.2757894736842,
                "left": 75.28276315789473,
                "top": 241.9679358717435
            },
            "points": [
                {
                    "x": 75.28276315789473,
                    "y": 241.9679358717435
                },
                {
                    "x": 759.5585526315789,
                    "y": 241.9679358717435
                },
                {
                    "x": 759.5585526315789,
                    "y": 326.4909819639279
                },
                {
                    "x": 75.28276315789473,
                    "y": 326.4909819639279
                }
            ]
        },
        {
            "id": "SLBMuuDFA",
            "type": "RECTANGLE",
            "tags": [
                "footer"
            ],
            "boundingBox": {
                "height": 213.7935871743487,
                "width": 690.9031578947369,
                "left": 75.28276315789473,
                "top": 39.77555110220441
            },
            "points": [
                {
                    "x": 75.28276315789473,
                    "y": 39.77555110220441
                },
                {
                    "x": 766.1859210526316,
                    "y": 39.77555110220441
                },
                {
                    "x": 766.1859210526316,
                    "y": 253.5691382765531
                },
                {
                    "x": 75.28276315789473,
                    "y": 253.5691382765531
                }
            ]
        }
    ],
    "version": "2.2.0"
}