{
    "asset": {
        "format": "png",
        "id": "78c9cc68719e9fb49a3fa7996fd85a46",
        "name": "C_073d3cdc3a4d5bb3b2902739db520f.png",
        "path": "file:C:/Repositories/BS.ReceiptAnalyzer/machine-learning-data/receipt-partitioning/images/C_073d3cdc3a4d5bb3b2902739db520f.png",
        "size": {
            "width": 702,
            "height": 1171
        },
        "state": 2,
        "type": 1
    },
    "regions": [
        {
            "id": "li3QNTSGn",
            "type": "RECTANGLE",
            "tags": [
                "header"
            ],
            "boundingBox": {
                "height": 187.56277056277057,
                "width": 618.3682310469314,
                "left": 65.85209837545126,
                "top": 898.5270562770563
            },
            "points": [
                {
                    "x": 65.85209837545126,
                    "y": 898.5270562770563
                },
                {
                    "x": 684.2203294223826,
                    "y": 898.5270562770563
                },
                {
                    "x": 684.2203294223826,
                    "y": 1086.0898268398269
                },
                {
                    "x": 65.85209837545126,
                    "y": 1086.0898268398269
                }
            ]
        },
        {
            "id": "4z_qLxS6W",
            "type": "RECTANGLE",
            "tags": [
                "product"
            ],
            "boundingBox": {
                "height": 65.9004329004329,
                "width": 638.6425992779783,
                "left": 53.180618231046935,
                "top": 814.8841991341992
            },
            "points": [
                {
                    "x": 53.180618231046935,
                    "y": 814.8841991341992
                },
                {
                    "x": 691.8232175090253,
                    "y": 814.8841991341992
                },
                {
                    "x": 691.8232175090253,
                    "y": 880.7846320346321
                },
                {
                    "x": 53.180618231046935,
                    "y": 880.7846320346321
                }
            ]
        },
        {
            "id": "LVMy2mb3c",
            "type": "RECTANGLE",
            "tags": [
                "product"
            ],
            "boundingBox": {
                "height": 48.15800865800866,
                "width": 631.0397111913358,
                "left": 55.7149142599278,
                "top": 769.2608225108225
            },
            "points": [
                {
                    "x": 55.7149142599278,
                    "y": 769.2608225108225
                },
                {
                    "x": 686.7546254512636,
                    "y": 769.2608225108225
                },
                {
                    "x": 686.7546254512636,
                    "y": 817.4188311688313
                },
                {
                    "x": 55.7149142599278,
                    "y": 817.4188311688313
                }
            ]
        },
        {
            "id": "W_disGiGJ",
            "type": "RECTANGLE",
            "tags": [
                "product"
            ],
            "boundingBox": {
                "height": 63.36580086580087,
                "width": 631.0397111913359,
                "left": 53.18061823104694,
                "top": 723.6374458874459
            },
            "points": [
                {
                    "x": 53.18061823104694,
                    "y": 723.6374458874459
                },
                {
                    "x": 684.2203294223829,
                    "y": 723.6374458874459
                },
                {
                    "x": 684.2203294223829,
                    "y": 787.0032467532468
                },
                {
                    "x": 53.18061823104694,
                    "y": 787.0032467532468
                }
            ]
        },
        {
            "id": "tBE46nJo5",
            "type": "RECTANGLE",
            "tags": [
                "vat-summary"
            ],
            "boundingBox": {
                "height": 172.35497835497836,
                "width": 618.3682310469314,
                "left": 63.317802346570396,
                "top": 553.8170995670996
            },
            "points": [
                {
                    "x": 63.317802346570396,
                    "y": 553.8170995670996
                },
                {
                    "x": 681.6860333935018,
                    "y": 553.8170995670996
                },
                {
                    "x": 681.6860333935018,
                    "y": 726.172077922078
                },
                {
                    "x": 63.317802346570396,
                    "y": 726.172077922078
                }
            ]
        },
        {
            "id": "3E7GWV9Iy",
            "type": "RECTANGLE",
            "tags": [
                "price-summary"
            ],
            "boundingBox": {
                "height": 103.91991341991343,
                "width": 643.7111913357401,
                "left": 43.04343411552347,
                "top": 457.50108225108227
            },
            "points": [
                {
                    "x": 43.04343411552347,
                    "y": 457.50108225108227
                },
                {
                    "x": 686.7546254512636,
                    "y": 457.50108225108227
                },
                {
                    "x": 686.7546254512636,
                    "y": 561.4209956709957
                },
                {
                    "x": 43.04343411552347,
                    "y": 561.4209956709957
                }
            ]
        },
        {
            "id": "ZcFI3T6rU",
            "type": "RECTANGLE",
            "tags": [
                "footer"
            ],
            "boundingBox": {
                "height": 162.21645021645023,
                "width": 646.245487364621,
                "left": 37.974842057761734,
                "top": 290.215367965368
            },
            "points": [
                {
                    "x": 37.974842057761734,
                    "y": 290.215367965368
                },
                {
                    "x": 684.2203294223826,
                    "y": 290.215367965368
                },
                {
                    "x": 684.2203294223826,
                    "y": 452.4318181818182
                },
                {
                    "x": 37.974842057761734,
                    "y": 452.4318181818182
                }
            ]
        }
    ],
    "version": "2.2.0"
}