{
    "asset": {
        "format": "png",
        "id": "7b163a043bdb126a080aa0668304c51e",
        "name": "B_4bba2552684f449f96c9bd73276b97.png",
        "path": "file:C:/Repositories/BS.ReceiptAnalyzer/machine-learning-data/receipt-partitioning/images/B_4bba2552684f449f96c9bd73276b97.png",
        "size": {
            "width": 1126,
            "height": 587
        },
        "state": 2,
        "type": 1
    },
    "regions": [
        {
            "id": "nBHSyrq3t",
            "type": "RECTANGLE",
            "tags": [
                "header"
            ],
            "boundingBox": {
                "height": 519.6952104499275,
                "width": 199.45798637395913,
                "left": 815.3058289174868,
                "top": 23.295763788098693
            },
            "points": [
                {
                    "x": 815.3058289174868,
                    "y": 23.295763788098693
                },
                {
                    "x": 1014.7638152914459,
                    "y": 23.295763788098693
                },
                {
                    "x": 1014.7638152914459,
                    "y": 542.9909742380261
                },
                {
                    "x": 815.3058289174868,
                    "y": 542.9909742380261
                }
            ]
        },
        {
            "id": "Buw3IJewc",
            "type": "RECTANGLE",
            "tags": [
                "product"
            ],
            "boundingBox": {
                "height": 519.6952104499275,
                "width": 76.71461014383043,
                "left": 719.8387585162756,
                "top": 23.295763788098693
            },
            "points": [
                {
                    "x": 719.8387585162756,
                    "y": 23.295763788098693
                },
                {
                    "x": 796.553368660106,
                    "y": 23.295763788098693
                },
                {
                    "x": 796.553368660106,
                    "y": 542.9909742380261
                },
                {
                    "x": 719.8387585162756,
                    "y": 542.9909742380261
                }
            ]
        },
        {
            "id": "MFopUMU9m",
            "type": "RECTANGLE",
            "tags": [
                "product"
            ],
            "boundingBox": {
                "height": 524.8069666182873,
                "width": 73.30507191521575,
                "left": 655.0575321725966,
                "top": 23.295763788098693
            },
            "points": [
                {
                    "x": 655.0575321725966,
                    "y": 23.295763788098693
                },
                {
                    "x": 728.3626040878122,
                    "y": 23.295763788098693
                },
                {
                    "x": 728.3626040878122,
                    "y": 548.1027304063861
                },
                {
                    "x": 655.0575321725966,
                    "y": 548.1027304063861
                }
            ]
        },
        {
            "id": "N0bpA_LA_",
            "type": "RECTANGLE",
            "tags": [
                "product"
            ],
            "boundingBox": {
                "height": 524.8069666182873,
                "width": 68.19076457229372,
                "left": 590.2763058289174,
                "top": 21.591845065312047
            },
            "points": [
                {
                    "x": 590.2763058289174,
                    "y": 21.591845065312047
                },
                {
                    "x": 658.4670704012112,
                    "y": 21.591845065312047
                },
                {
                    "x": 658.4670704012112,
                    "y": 546.3988116835994
                },
                {
                    "x": 590.2763058289174,
                    "y": 546.3988116835994
                }
            ]
        },
        {
            "id": "TvfcTq9KQ",
            "type": "RECTANGLE",
            "tags": [
                "product"
            ],
            "boundingBox": {
                "height": 524.8069666182873,
                "width": 68.19076457229372,
                "left": 523.7903103709311,
                "top": 19.887926342525397
            },
            "points": [
                {
                    "x": 523.7903103709311,
                    "y": 19.887926342525397
                },
                {
                    "x": 591.9810749432248,
                    "y": 19.887926342525397
                },
                {
                    "x": 591.9810749432248,
                    "y": 544.6948929608127
                },
                {
                    "x": 523.7903103709311,
                    "y": 544.6948929608127
                }
            ]
        },
        {
            "id": "MfRraMD4s",
            "type": "RECTANGLE",
            "tags": [
                "product"
            ],
            "boundingBox": {
                "height": 531.622641509434,
                "width": 71.6003028009084,
                "left": 455.5995457986374,
                "top": 16.480088896952104
            },
            "points": [
                {
                    "x": 455.5995457986374,
                    "y": 16.480088896952104
                },
                {
                    "x": 527.1998485995458,
                    "y": 16.480088896952104
                },
                {
                    "x": 527.1998485995458,
                    "y": 548.1027304063861
                },
                {
                    "x": 455.5995457986374,
                    "y": 548.1027304063861
                }
            ]
        },
        {
            "id": "tFEepCIxS",
            "type": "RECTANGLE",
            "tags": [
                "product"
            ],
            "boundingBox": {
                "height": 531.622641509434,
                "width": 75.00984102952309,
                "left": 383.99924299772897,
                "top": 16.480088896952104
            },
            "points": [
                {
                    "x": 383.99924299772897,
                    "y": 16.480088896952104
                },
                {
                    "x": 459.0090840272521,
                    "y": 16.480088896952104
                },
                {
                    "x": 459.0090840272521,
                    "y": 548.1027304063861
                },
                {
                    "x": 383.99924299772897,
                    "y": 548.1027304063861
                }
            ]
        },
        {
            "id": "J8Dmr3HE3",
            "type": "RECTANGLE",
            "tags": [
                "vat-summary"
            ],
            "boundingBox": {
                "height": 533.3265602322206,
                "width": 93.76230128690386,
                "left": 264.665404996215,
                "top": 19.887926342525397
            },
            "points": [
                {
                    "x": 264.665404996215,
                    "y": 19.887926342525397
                },
                {
                    "x": 358.4277062831188,
                    "y": 19.887926342525397
                },
                {
                    "x": 358.4277062831188,
                    "y": 553.2144865747459
                },
                {
                    "x": 264.665404996215,
                    "y": 553.2144865747459
                }
            ]
        },
        {
            "id": "hiNQ6lj4D",
            "type": "RECTANGLE",
            "tags": [
                "price-summary"
            ],
            "boundingBox": {
                "height": 529.9187227866473,
                "width": 81.82891748675246,
                "left": 208.40802422407268,
                "top": 21.591845065312047
            },
            "points": [
                {
                    "x": 208.40802422407268,
                    "y": 21.591845065312047
                },
                {
                    "x": 290.23694171082514,
                    "y": 21.591845065312047
                },
                {
                    "x": 290.23694171082514,
                    "y": 551.5105678519593
                },
                {
                    "x": 208.40802422407268,
                    "y": 551.5105678519593
                }
            ]
        },
        {
            "id": "eYx3vxHoR",
            "type": "RECTANGLE",
            "tags": [
                "footer"
            ],
            "boundingBox": {
                "height": 533.3265602322203,
                "width": 161.52687358062073,
                "left": 60.519303557910675,
                "top": 23.295763788098682
            },
            "points": [
                {
                    "x": 60.519303557910675,
                    "y": 23.295763788098682
                },
                {
                    "x": 222.04617713853142,
                    "y": 23.295763788098682
                },
                {
                    "x": 222.04617713853142,
                    "y": 556.6223240203191
                },
                {
                    "x": 60.519303557910675,
                    "y": 556.6223240203191
                }
            ]
        }
    ],
    "version": "2.2.0"
}