{
    "asset": {
        "format": "png",
        "id": "8a3ca652163d37e437602f41f6dc3a12",
        "name": "D_4827d36719442e844ab83f43b8981d.png",
        "path": "file:C:/Repositories/BS.ReceiptAnalyzer/machine-learning-data/receipt-partitioning/images/D_4827d36719442e844ab83f43b8981d.png",
        "size": {
            "width": 1185,
            "height": 710
        },
        "state": 2,
        "type": 1
    },
    "regions": [
        {
            "id": "3eWre8Uxv",
            "type": "RECTANGLE",
            "tags": [
                "header"
            ],
            "boundingBox": {
                "height": 640.7942238267148,
                "width": 258.0173035328046,
                "left": 24.34931506849315,
                "top": 58.53922232250301
            },
            "points": [
                {
                    "x": 24.34931506849315,
                    "y": 58.53922232250301
                },
                {
                    "x": 282.3666186012978,
                    "y": 58.53922232250301
                },
                {
                    "x": 282.3666186012978,
                    "y": 699.3334461492178
                },
                {
                    "x": 24.34931506849315,
                    "y": 699.3334461492178
                }
            ]
        },
        {
            "id": "n6UKRjUF_",
            "type": "RECTANGLE",
            "tags": [
                "product"
            ],
            "boundingBox": {
                "height": 649.3381468110709,
                "width": 70.05767844268205,
                "left": 302.8713049747657,
                "top": 56.83043772563177
            },
            "points": [
                {
                    "x": 302.8713049747657,
                    "y": 56.83043772563177
                },
                {
                    "x": 372.92898341744774,
                    "y": 56.83043772563177
                },
                {
                    "x": 372.92898341744774,
                    "y": 706.1685845367027
                },
                {
                    "x": 302.8713049747657,
                    "y": 706.1685845367027
                }
            ]
        },
        {
            "id": "3gQhWWw1R",
            "type": "RECTANGLE",
            "tags": [
                "vat-summary"
            ],
            "boundingBox": {
                "height": 630.5415162454873,
                "width": 109.35832732516222,
                "left": 384.89005046863736,
                "top": 77.33585288808663
            },
            "points": [
                {
                    "x": 384.89005046863736,
                    "y": 77.33585288808663
                },
                {
                    "x": 494.2483777937996,
                    "y": 77.33585288808663
                },
                {
                    "x": 494.2483777937996,
                    "y": 707.877369133574
                },
                {
                    "x": 384.89005046863736,
                    "y": 707.877369133574
                }
            ]
        },
        {
            "id": "jtsgkXwAh",
            "type": "RECTANGLE",
            "tags": [
                "price-summary"
            ],
            "boundingBox": {
                "height": 654.4645006016847,
                "width": 73.47512617159337,
                "left": 477.16113914924296,
                "top": 51.70408393501805
            },
            "points": [
                {
                    "x": 477.16113914924296,
                    "y": 51.70408393501805
                },
                {
                    "x": 550.6362653208363,
                    "y": 51.70408393501805
                },
                {
                    "x": 550.6362653208363,
                    "y": 706.1685845367027
                },
                {
                    "x": 477.16113914924296,
                    "y": 706.1685845367027
                }
            ]
        },
        {
            "id": "REle0fK7N",
            "type": "RECTANGLE",
            "tags": [
                "footer"
            ],
            "boundingBox": {
                "height": 675.3837620336943,
                "width": 254.5998558038933,
                "left": 560.8886085075703,
                "top": 34.616237966305654
            },
            "points": [
                {
                    "x": 560.8886085075703,
                    "y": 34.616237966305654
                },
                {
                    "x": 815.4884643114636,
                    "y": 34.616237966305654
                },
                {
                    "x": 815.4884643114636,
                    "y": 710
                },
                {
                    "x": 560.8886085075703,
                    "y": 710
                }
            ]
        }
    ],
    "version": "2.2.0"
}