{
    "asset": {
        "format": "png",
        "id": "b0aa92b419513f48cffcb8c9e6a55134",
        "name": "D_ea538cd0cb4cf0a5552dc438be076d.png",
        "path": "file:C:/Repositories/BS.ReceiptAnalyzer/machine-learning-data/receipt-partitioning/images/D_ea538cd0cb4cf0a5552dc438be076d.png",
        "size": {
            "width": 1162,
            "height": 632
        },
        "state": 2,
        "type": 1
    },
    "regions": [
        {
            "id": "IPPyaqdIH",
            "type": "RECTANGLE",
            "tags": [
                "header"
            ],
            "boundingBox": {
                "height": 542.4824037184595,
                "width": 137.5942238267148,
                "left": 49.919855595667876,
                "top": 89.5175962815405
            },
            "points": [
                {
                    "x": 49.919855595667876,
                    "y": 89.5175962815405
                },
                {
                    "x": 187.51407942238268,
                    "y": 89.5175962815405
                },
                {
                    "x": 187.51407942238268,
                    "y": 632
                },
                {
                    "x": 49.919855595667876,
                    "y": 632
                }
            ]
        },
        {
            "id": "TsC-88uka",
            "type": "RECTANGLE",
            "tags": [
                "product"
            ],
            "boundingBox": {
                "height": 540.515272244356,
                "width": 44.04693140794227,
                "left": 190.87003610108303,
                "top": 91.19621513944222
            },
            "points": [
                {
                    "x": 190.87003610108303,
                    "y": 91.19621513944222
                },
                {
                    "x": 234.91696750902528,
                    "y": 91.19621513944222
                },
                {
                    "x": 234.91696750902528,
                    "y": 631.7114873837982
                },
                {
                    "x": 190.87003610108303,
                    "y": 631.7114873837982
                }
            ]
        },
        {
            "id": "T-YZJv6rd",
            "type": "RECTANGLE",
            "tags": [
                "product"
            ],
            "boundingBox": {
                "height": 535.4794156706507,
                "width": 41.94945848375451,
                "left": 214.36173285198558,
                "top": 95.39276228419655
            },
            "points": [
                {
                    "x": 214.36173285198558,
                    "y": 95.39276228419655
                },
                {
                    "x": 256.3111913357401,
                    "y": 95.39276228419655
                },
                {
                    "x": 256.3111913357401,
                    "y": 630.8721779548473
                },
                {
                    "x": 214.36173285198558,
                    "y": 630.8721779548473
                }
            ]
        },
        {
            "id": "FmX11hMrC",
            "type": "RECTANGLE",
            "tags": [
                "product"
            ],
            "boundingBox": {
                "height": 532.1221779548473,
                "width": 40.271480144404336,
                "left": 239.53140794223827,
                "top": 98.75
            },
            "points": [
                {
                    "x": 239.53140794223827,
                    "y": 98.75
                },
                {
                    "x": 279.8028880866426,
                    "y": 98.75
                },
                {
                    "x": 279.8028880866426,
                    "y": 630.8721779548473
                },
                {
                    "x": 239.53140794223827,
                    "y": 630.8721779548473
                }
            ]
        },
        {
            "id": "A0hnrBi4V",
            "type": "RECTANGLE",
            "tags": [
                "product"
            ],
            "boundingBox": {
                "height": 528.7649402390439,
                "width": 40.271480144404336,
                "left": 266.37906137184115,
                "top": 102.10723771580345
            },
            "points": [
                {
                    "x": 266.37906137184115,
                    "y": 102.10723771580345
                },
                {
                    "x": 306.6505415162455,
                    "y": 102.10723771580345
                },
                {
                    "x": 306.6505415162455,
                    "y": 630.8721779548473
                },
                {
                    "x": 266.37906137184115,
                    "y": 630.8721779548473
                }
            ]
        },
        {
            "id": "sPkv62Sae",
            "type": "RECTANGLE",
            "tags": [
                "product"
            ],
            "boundingBox": {
                "height": 525.4077025232403,
                "width": 38.59350180505415,
                "left": 291.54873646209387,
                "top": 105.46447543160691
            },
            "points": [
                {
                    "x": 291.54873646209387,
                    "y": 105.46447543160691
                },
                {
                    "x": 330.14223826714806,
                    "y": 105.46447543160691
                },
                {
                    "x": 330.14223826714806,
                    "y": 630.8721779548473
                },
                {
                    "x": 291.54873646209387,
                    "y": 630.8721779548473
                }
            ]
        },
        {
            "id": "1MeXnjBJb",
            "type": "RECTANGLE",
            "tags": [
                "product"
            ],
            "boundingBox": {
                "height": 525.4077025232403,
                "width": 36.91552346570397,
                "left": 316.7184115523466,
                "top": 105.46447543160691
            },
            "points": [
                {
                    "x": 316.7184115523466,
                    "y": 105.46447543160691
                },
                {
                    "x": 353.6339350180506,
                    "y": 105.46447543160691
                },
                {
                    "x": 353.6339350180506,
                    "y": 630.8721779548473
                },
                {
                    "x": 316.7184115523466,
                    "y": 630.8721779548473
                }
            ]
        },
        {
            "id": "J7tK8Puwt",
            "type": "RECTANGLE",
            "tags": [
                "product"
            ],
            "boundingBox": {
                "height": 523.7290836653386,
                "width": 36.91552346570397,
                "left": 340.2101083032491,
                "top": 107.14309428950864
            },
            "points": [
                {
                    "x": 340.2101083032491,
                    "y": 107.14309428950864
                },
                {
                    "x": 377.1256317689531,
                    "y": 107.14309428950864
                },
                {
                    "x": 377.1256317689531,
                    "y": 630.8721779548473
                },
                {
                    "x": 340.2101083032491,
                    "y": 630.8721779548473
                }
            ]
        },
        {
            "id": "ed23GspTe",
            "type": "RECTANGLE",
            "tags": [
                "product"
            ],
            "boundingBox": {
                "height": 523.7290836653386,
                "width": 33.55956678700361,
                "left": 367.057761732852,
                "top": 107.14309428950864
            },
            "points": [
                {
                    "x": 367.057761732852,
                    "y": 107.14309428950864
                },
                {
                    "x": 400.6173285198556,
                    "y": 107.14309428950864
                },
                {
                    "x": 400.6173285198556,
                    "y": 630.8721779548473
                },
                {
                    "x": 367.057761732852,
                    "y": 630.8721779548473
                }
            ]
        },
        {
            "id": "mhcGwmMR2",
            "type": "RECTANGLE",
            "tags": [
                "product"
            ],
            "boundingBox": {
                "height": 525.4077025232403,
                "width": 35.237545126353794,
                "left": 388.87148014440436,
                "top": 105.46447543160691
            },
            "points": [
                {
                    "x": 388.87148014440436,
                    "y": 105.46447543160691
                },
                {
                    "x": 424.10902527075814,
                    "y": 105.46447543160691
                },
                {
                    "x": 424.10902527075814,
                    "y": 630.8721779548473
                },
                {
                    "x": 388.87148014440436,
                    "y": 630.8721779548473
                }
            ]
        },
        {
            "id": "Dy-0UQuPq",
            "type": "RECTANGLE",
            "tags": [
                "product"
            ],
            "boundingBox": {
                "height": 523.7290836653386,
                "width": 33.55956678700361,
                "left": 414.0411552346571,
                "top": 107.14309428950864
            },
            "points": [
                {
                    "x": 414.0411552346571,
                    "y": 107.14309428950864
                },
                {
                    "x": 447.60072202166066,
                    "y": 107.14309428950864
                },
                {
                    "x": 447.60072202166066,
                    "y": 630.8721779548473
                },
                {
                    "x": 414.0411552346571,
                    "y": 630.8721779548473
                }
            ]
        },
        {
            "id": "76JeTSnui",
            "type": "RECTANGLE",
            "tags": [
                "product"
            ],
            "boundingBox": {
                "height": 523.7290836653386,
                "width": 33.55956678700361,
                "left": 437.5328519855596,
                "top": 107.14309428950864
            },
            "points": [
                {
                    "x": 437.5328519855596,
                    "y": 107.14309428950864
                },
                {
                    "x": 471.0924187725632,
                    "y": 107.14309428950864
                },
                {
                    "x": 471.0924187725632,
                    "y": 630.8721779548473
                },
                {
                    "x": 437.5328519855596,
                    "y": 630.8721779548473
                }
            ]
        },
        {
            "id": "oqslz_H1q",
            "type": "RECTANGLE",
            "tags": [
                "product"
            ],
            "boundingBox": {
                "height": 523.7290836653386,
                "width": 33.55956678700361,
                "left": 461.0245487364621,
                "top": 105.46447543160691
            },
            "points": [
                {
                    "x": 461.0245487364621,
                    "y": 105.46447543160691
                },
                {
                    "x": 494.58411552346575,
                    "y": 105.46447543160691
                },
                {
                    "x": 494.58411552346575,
                    "y": 629.1935590969456
                },
                {
                    "x": 461.0245487364621,
                    "y": 629.1935590969456
                }
            ]
        },
        {
            "id": "KjNXlPwhw",
            "type": "RECTANGLE",
            "tags": [
                "product"
            ],
            "boundingBox": {
                "height": 525.4077025232403,
                "width": 31.88158844765343,
                "left": 486.19422382671485,
                "top": 105.46447543160691
            },
            "points": [
                {
                    "x": 486.19422382671485,
                    "y": 105.46447543160691
                },
                {
                    "x": 518.0758122743682,
                    "y": 105.46447543160691
                },
                {
                    "x": 518.0758122743682,
                    "y": 630.8721779548473
                },
                {
                    "x": 486.19422382671485,
                    "y": 630.8721779548473
                }
            ]
        },
        {
            "id": "3kXnIsMzd",
            "type": "RECTANGLE",
            "tags": [
                "product"
            ],
            "boundingBox": {
                "height": 520.3718459495352,
                "width": 35.237545126353794,
                "left": 508.00794223826716,
                "top": 108.82171314741036
            },
            "points": [
                {
                    "x": 508.00794223826716,
                    "y": 108.82171314741036
                },
                {
                    "x": 543.245487364621,
                    "y": 108.82171314741036
                },
                {
                    "x": 543.245487364621,
                    "y": 629.1935590969456
                },
                {
                    "x": 508.00794223826716,
                    "y": 629.1935590969456
                }
            ]
        },
        {
            "id": "J0Hx4SJlL",
            "type": "RECTANGLE",
            "tags": [
                "vat-summary"
            ],
            "boundingBox": {
                "height": 528.7649402390439,
                "width": 127.52635379061373,
                "left": 541.5675090252707,
                "top": 102.10723771580345
            },
            "points": [
                {
                    "x": 541.5675090252707,
                    "y": 102.10723771580345
                },
                {
                    "x": 669.0938628158846,
                    "y": 102.10723771580345
                },
                {
                    "x": 669.0938628158846,
                    "y": 630.8721779548473
                },
                {
                    "x": 541.5675090252707,
                    "y": 630.8721779548473
                }
            ]
        },
        {
            "id": "M0fBDFW7V",
            "type": "RECTANGLE",
            "tags": [
                "price-summary"
            ],
            "boundingBox": {
                "height": 530.4435590969456,
                "width": 58.72924187725632,
                "left": 659.0259927797835,
                "top": 98.75
            },
            "points": [
                {
                    "x": 659.0259927797835,
                    "y": 98.75
                },
                {
                    "x": 717.7552346570398,
                    "y": 98.75
                },
                {
                    "x": 717.7552346570398,
                    "y": 629.1935590969456
                },
                {
                    "x": 659.0259927797835,
                    "y": 629.1935590969456
                }
            ]
        },
        {
            "id": "QPl7ZrHhs",
            "type": "RECTANGLE",
            "tags": [
                "footer"
            ],
            "boundingBox": {
                "height": 538.8366533864543,
                "width": 132.56028880866427,
                "left": 721.1111913357402,
                "top": 92.0355245683931
            },
            "points": [
                {
                    "x": 721.1111913357402,
                    "y": 92.0355245683931
                },
                {
                    "x": 853.6714801444044,
                    "y": 92.0355245683931
                },
                {
                    "x": 853.6714801444044,
                    "y": 630.8721779548473
                },
                {
                    "x": 721.1111913357402,
                    "y": 630.8721779548473
                }
            ]
        }
    ],
    "version": "2.2.0"
}