{
    "asset": {
        "format": "png",
        "id": "d11fef73e0cb20445f8e1eab23bd7370",
        "name": "A_b5fb3573be8d4d1e96ec59670b53fe48.png",
        "path": "file:C:/Repositories/BS.ReceiptAnalyzer/machine-learning-data/receipt-partitioning/images/A_b5fb3573be8d4d1e96ec59670b53fe48.png",
        "size": {
            "width": 495,
            "height": 1187
        },
        "state": 2,
        "type": 1
    },
    "regions": [
        {
            "id": "IHwMdx44l",
            "type": "RECTANGLE",
            "tags": [
                "header"
            ],
            "boundingBox": {
                "height": 102.28657314629258,
                "width": 404.56730769230774,
                "left": 59.60674579326923,
                "top": 158.187374749499
            },
            "points": [
                {
                    "x": 59.60674579326923,
                    "y": 158.187374749499
                },
                {
                    "x": 464.17405348557696,
                    "y": 158.187374749499
                },
                {
                    "x": 464.17405348557696,
                    "y": 260.4739478957916
                },
                {
                    "x": 59.60674579326923,
                    "y": 260.4739478957916
                }
            ]
        },
        {
            "id": "mj-DSD8-d",
            "type": "RECTANGLE",
            "tags": [
                "product"
            ],
            "boundingBox": {
                "height": 30.923847695390783,
                "width": 409.3269230769231,
                "left": 57.22693810096154,
                "top": 262.85270541082167
            },
            "points": [
                {
                    "x": 57.22693810096154,
                    "y": 262.85270541082167
                },
                {
                    "x": 466.55386117788464,
                    "y": 262.85270541082167
                },
                {
                    "x": 466.55386117788464,
                    "y": 293.7765531062124
                },
                {
                    "x": 57.22693810096154,
                    "y": 293.7765531062124
                }
            ]
        },
        {
            "id": "sEcYjnxbB",
            "type": "RECTANGLE",
            "tags": [
                "product"
            ],
            "boundingBox": {
                "height": 30.923847695390783,
                "width": 411.70673076923083,
                "left": 57.22693810096154,
                "top": 281.88276553106215
            },
            "points": [
                {
                    "x": 57.22693810096154,
                    "y": 281.88276553106215
                },
                {
                    "x": 468.9336688701923,
                    "y": 281.88276553106215
                },
                {
                    "x": 468.9336688701923,
                    "y": 312.8066132264529
                },
                {
                    "x": 57.22693810096154,
                    "y": 312.8066132264529
                }
            ]
        },
        {
            "id": "rAFTAjx1j",
            "type": "RECTANGLE",
            "tags": [
                "product"
            ],
            "boundingBox": {
                "height": 30.923847695390783,
                "width": 411.70673076923083,
                "left": 54.847130408653854,
                "top": 298.53406813627254
            },
            "points": [
                {
                    "x": 54.847130408653854,
                    "y": 298.53406813627254
                },
                {
                    "x": 466.55386117788464,
                    "y": 298.53406813627254
                },
                {
                    "x": 466.55386117788464,
                    "y": 329.45791583166334
                },
                {
                    "x": 54.847130408653854,
                    "y": 329.45791583166334
                }
            ]
        },
        {
            "id": "QD2xB1RbF",
            "type": "RECTANGLE",
            "tags": [
                "product"
            ],
            "boundingBox": {
                "height": 30.923847695390783,
                "width": 411.70673076923083,
                "left": 54.847130408653854,
                "top": 317.564128256513
            },
            "points": [
                {
                    "x": 54.847130408653854,
                    "y": 317.564128256513
                },
                {
                    "x": 466.55386117788464,
                    "y": 317.564128256513
                },
                {
                    "x": 466.55386117788464,
                    "y": 348.4879759519038
                },
                {
                    "x": 54.847130408653854,
                    "y": 348.4879759519038
                }
            ]
        },
        {
            "id": "VVV1nqvMA",
            "type": "RECTANGLE",
            "tags": [
                "product"
            ],
            "boundingBox": {
                "height": 30.923847695390783,
                "width": 414.0865384615385,
                "left": 52.46732271634616,
                "top": 334.21543086172346
            },
            "points": [
                {
                    "x": 52.46732271634616,
                    "y": 334.21543086172346
                },
                {
                    "x": 466.55386117788464,
                    "y": 334.21543086172346
                },
                {
                    "x": 466.55386117788464,
                    "y": 365.1392785571142
                },
                {
                    "x": 52.46732271634616,
                    "y": 365.1392785571142
                }
            ]
        },
        {
            "id": "TlHuf8N9o",
            "type": "RECTANGLE",
            "tags": [
                "vat-summary"
            ],
            "boundingBox": {
                "height": 47.5751503006012,
                "width": 414.0865384615385,
                "left": 52.46732271634616,
                "top": 358.00300601202406
            },
            "points": [
                {
                    "x": 52.46732271634616,
                    "y": 358.00300601202406
                },
                {
                    "x": 466.55386117788464,
                    "y": 358.00300601202406
                },
                {
                    "x": 466.55386117788464,
                    "y": 405.57815631262525
                },
                {
                    "x": 52.46732271634616,
                    "y": 405.57815631262525
                }
            ]
        },
        {
            "id": "q90POKDgP",
            "type": "RECTANGLE",
            "tags": [
                "price-summary"
            ],
            "boundingBox": {
                "height": 45.19639278557114,
                "width": 418.84615384615387,
                "left": 50.08751502403847,
                "top": 396.063126252505
            },
            "points": [
                {
                    "x": 50.08751502403847,
                    "y": 396.063126252505
                },
                {
                    "x": 468.9336688701923,
                    "y": 396.063126252505
                },
                {
                    "x": 468.9336688701923,
                    "y": 441.2595190380762
                },
                {
                    "x": 50.08751502403847,
                    "y": 441.2595190380762
                }
            ]
        },
        {
            "id": "HbfoBSFQ4",
            "type": "RECTANGLE",
            "tags": [
                "footer"
            ],
            "boundingBox": {
                "height": 701.7334669338677,
                "width": 452.05190805288464,
                "left": 33.42886117788462,
                "top": 429.36573146292585
            },
            "points": [
                {
                    "x": 33.42886117788462,
                    "y": 429.36573146292585
                },
                {
                    "x": 485.4807692307693,
                    "y": 429.36573146292585
                },
                {
                    "x": 485.4807692307693,
                    "y": 1131.0991983967936
                },
                {
                    "x": 33.42886117788462,
                    "y": 1131.0991983967936
                }
            ]
        }
    ],
    "version": "2.2.0"
}