{
    "asset": {
        "format": "png",
        "id": "d4a344611cad0fa57217be79e8c4a019",
        "name": "A_ba65444523fe4e59a57f46ce2c411127.png",
        "path": "file:C:/Repositories/BS.ReceiptAnalyzer/machine-learning-data/receipt-partitioning/images/A_ba65444523fe4e59a57f46ce2c411127.png",
        "size": {
            "width": 833,
            "height": 1006
        },
        "state": 2,
        "type": 1
    },
    "regions": [
        {
            "id": "NtZF8TvCk",
            "type": "RECTANGLE",
            "tags": [
                "header"
            ],
            "boundingBox": {
                "height": 227.81162324649299,
                "width": 774.5084745762712,
                "left": 15.33196504237288,
                "top": 180.43486973947896
            },
            "points": [
                {
                    "x": 15.33196504237288,
                    "y": 180.43486973947896
                },
                {
                    "x": 789.840439618644,
                    "y": 180.43486973947896
                },
                {
                    "x": 789.840439618644,
                    "y": 408.24649298597194
                },
                {
                    "x": 15.33196504237288,
                    "y": 408.24649298597194
                }
            ]
        },
        {
            "id": "gL1ZFNdIG",
            "type": "RECTANGLE",
            "tags": [
                "product"
            ],
            "boundingBox": {
                "height": 60.480961923847694,
                "width": 778.542372881356,
                "left": 9.281117584745763,
                "top": 416.31062124248496
            },
            "points": [
                {
                    "x": 9.281117584745763,
                    "y": 416.31062124248496
                },
                {
                    "x": 787.8234904661017,
                    "y": 416.31062124248496
                },
                {
                    "x": 787.8234904661017,
                    "y": 476.79158316633266
                },
                {
                    "x": 9.281117584745763,
                    "y": 476.79158316633266
                }
            ]
        },
        {
            "id": "ls330cUDS",
            "type": "RECTANGLE",
            "tags": [
                "vat-summary"
            ],
            "boundingBox": {
                "height": 129.02605210420842,
                "width": 784.5932203389831,
                "left": 7.264168432203389,
                "top": 468.72745490981964
            },
            "points": [
                {
                    "x": 7.264168432203389,
                    "y": 468.72745490981964
                },
                {
                    "x": 791.8573887711864,
                    "y": 468.72745490981964
                },
                {
                    "x": 791.8573887711864,
                    "y": 597.7535070140281
                },
                {
                    "x": 7.264168432203389,
                    "y": 597.7535070140281
                }
            ]
        },
        {
            "id": "8HBQmeHLC",
            "type": "RECTANGLE",
            "tags": [
                "price-summary"
            ],
            "boundingBox": {
                "height": 88.70541082164328,
                "width": 778.542372881356,
                "left": 13.315015889830509,
                "top": 577.5931863727455
            },
            "points": [
                {
                    "x": 13.315015889830509,
                    "y": 577.5931863727455
                },
                {
                    "x": 791.8573887711864,
                    "y": 577.5931863727455
                },
                {
                    "x": 791.8573887711864,
                    "y": 666.2985971943888
                },
                {
                    "x": 13.315015889830509,
                    "y": 666.2985971943888
                }
            ]
        },
        {
            "id": "QFOHLa4__",
            "type": "RECTANGLE",
            "tags": [
                "footer"
            ],
            "boundingBox": {
                "height": 312.48496993987976,
                "width": 800.728813559322,
                "left": 7.264168432203389,
                "top": 662.2665330661323
            },
            "points": [
                {
                    "x": 7.264168432203389,
                    "y": 662.2665330661323
                },
                {
                    "x": 807.9929819915254,
                    "y": 662.2665330661323
                },
                {
                    "x": 807.9929819915254,
                    "y": 974.7515030060121
                },
                {
                    "x": 7.264168432203389,
                    "y": 974.7515030060121
                }
            ]
        }
    ],
    "version": "2.2.0"
}